multistream/__init__.py
multistream/apps.py
multistream/config_parser.py
multistream/logger.py
multistream/nginx.py
multistream-0.0.1.dist-info/LICENSE
multistream-0.0.1.dist-info/METADATA
multistream-0.0.1.dist-info/WHEEL
multistream-0.0.1.dist-info/entry_points.txt
multistream-0.0.1.dist-info/top_level.txt
multistream-0.0.1.dist-info/RECORD
