Metadata-Version: 2.1
Name: multistream
Version: 0.0.1
Summary: Python application
Home-page: https://github.com/meteoritesolutions/multistream
Author: Meteorite Online Solutions, LLC
Author-email: engineering@meteoritesolutions.com
License: Proprietary
Keywords: Python
Platform: UNKNOWN
Classifier: Development Status :: 5 - Production/Stable
Classifier: Intended Audience :: Developers
Classifier: Intended Audience :: Information Technology
Classifier: Intended Audience :: System Administrators
Classifier: Programming Language :: Python :: 3.9
License-File: LICENSE
Requires-Dist: requests
Requires-Dist: crossplane
Requires-Dist: pyyaml
